Workbook

Sheet README
A1: Saudi Arabia: Blanchard-Leigh (2013) exercise on IMF non-oil projections
A3: Purpose
A4: Blanchard & Leigh (2013, AER P&P 'Growth Forecast Errors and Fiscal Multipliers') regress growth-forecast errors on the
A5: fiscal consolidation planned at forecast time: FE(t) = alpha + beta * planned consolidation(t) + eps. beta < 0 indicates
A6: fiscal multipliers larger than assumed by forecasters. This workbook adapts the design to Saudi Arabia's non-oil economy:
A7: - Outcome: real NON-OIL GDP growth, year t.
A8: - Fiscal variable: NON-OIL PRIMARY BALANCE (NOPB), percent of non-oil GDP.
A9: - Planned consolidation for t = NOPB(t) projection minus NOPB(t-1) estimate, both from the same pre-budget vintage.
A11: Projection vintages ('official projections')
A12: The Saudi authorities do not publish non-oil GDP growth or NOPB projections consistently, so per the task instruction the
A13: IMF staff projections closest before each budget's approval are used. Saudi budgets for year t are approved in Nov/Dec of
A14: t-1; the IMF Article IV staff report for Saudi Arabia is published Jul-Oct, i.e. 2-5 months before the budget. The vintage
... A44: cited IMF country reports; transcription verified against rendered table images.

Sheet Data
A1: Budget year t | B1: IMF vintage (pub. before t's budget) | C1: Vintage pub. | D1: Proj. non-oil real GDP growth t (%) | E1: Proj. NOPB t (% non-oil GDP) | F1: Est. NOPB t-1 (% non-oil GDP) | G1: Planned consolidation ΔNOPB (pp) | H1: Actual non-oil growth t, latest IMF (%) | I1: Actual NOPB t, latest IMF (%) | J1: Latest-actual source | K1: Forecast error, latest (pp) = H - D | L1: Actual non-oil growth t, first outturn (%) | M1: Actual NOPB t, first outturn (%) | N1: Actual NOPB t-1, same report (%) | O1: Actual ΔNOPB, first outturn (pp) | P1: First-outturn source | Q1: Forecast error, first outturn (pp) = L - D
A2: 2017 | B2: CR 16/326 (2016 Art. IV) | C2: Oct 2016 | D2: 2.7 | E2: -36.2 | F2: -39.3 | G2: =IF(AND(ISNUMBER(E2),ISNUMBER(F2)),E2-F2,"") | H2: 1.3 | I2: -39.6 | J2: CR 19/290 | K2: =IF(AND(ISNUMBER(H2),ISNUMBER(D2)),H2-D2,"") | L2: 1.1 | M2: -39.7 | N2: -45.7 | O2: =IF(AND(ISNUMBER(M2),ISNUMBER(N2)),M2-N2,"") | P2: CR 18/263 | Q2: =IF(AND(ISNUMBER(L2),ISNUMBER(D2)),L2-D2,"")
A3: 2018 | B3: CR 17/316 (2017 Art. IV) | C3: Oct 2017 | D3: 1.3 | E3: -34 | F3: -39.6 | G3: =IF(AND(ISNUMBER(E3),ISNUMBER(F3)),E3-F3,"") | H3: 2.1 | I3: -41.6 | J3: CR 19/290 | K3: =IF(AND(ISNUMBER(H3),ISNUMBER(D3)),H3-D3,"") | L3: 2.1 | M3: -41.6 | N3: -39.6 | O3: =IF(AND(ISNUMBER(M3),ISNUMBER(N3)),M3-N3,"") | P3: CR 19/290 | Q3: =IF(AND(ISNUMBER(L3),ISNUMBER(D3)),L3-D3,"")
A4: 2019 | B4: CR 18/263 (2018 Art. IV) | C4: Aug 2018 | D4: 2.1 | E4: -36.9 | F4: -41.7 | G4: =IF(AND(ISNUMBER(E4),ISNUMBER(F4)),E4-F4,"") | H4: 3.5 | I4: -34.7 | J4: CR 23/323 | K4: =IF(AND(ISNUMBER(H4),ISNUMBER(D4)),H4-D4,"") | L4: 3.3 | M4: -35.9 | O4: =IF(AND(ISNUMBER(M4),ISNUMBER(N4)),M4-N4,"") | P4: CR 21/149 (no 2018 column; prior year n.a.) | Q4: =IF(AND(ISNUMBER(L4),ISNUMBER(D4)),L4-D4,"")
A5: 2020 | B5: CR 19/290 (2019 Art. IV) | C5: Sep 2019 | D5: 2.7 | E5: -38.1 | F5: -41.1 | G5: =IF(AND(ISNUMBER(E5),ISNUMBER(F5)),E5-F5,"") | H5: -2.3 | I5: -37.2 | J5: CR 24/280 | K5: =IF(AND(ISNUMBER(H5),ISNUMBER(D5)),H5-D5,"") | L5: -2.3 | M5: -38.1 | N5: -35.9 | O5: =IF(AND(ISNUMBER(M5),ISNUMBER(N5)),M5-N5,"") | P5: CR 21/149 | Q5: =IF(AND(ISNUMBER(L5),ISNUMBER(D5)),L5-D5,"")
A6: 2021 | B6: none (no 2020 Art. IV; COVID) | C6: - | G6: =IF(AND(ISNUMBER(E6),ISNUMBER(F6)),E6-F6,"") | H6: 5.6 | I6: -29.1 | J6: CR 24/280 | K6: =IF(AND(ISNUMBER(H6),ISNUMBER(D6)),H6-D6,"") | L6: 4.9 | M6: -31.4 | N6: -39.7 | O6: =IF(AND(ISNUMBER(M6),ISNUMBER(N6)),M6-N6,"") | P6: CR 22/274 | Q6: =IF(AND(ISNUMBER(L6),ISNUMBER(D6)),L6-D6,"")
A7: 2022 | B7: CR 21/149 (2021 Art. IV) | C7: Jul 2021 | D7: 3.6 | E7: -25.7 | F7: -28.2 | G7: =IF(AND(ISNUMBER(E7),ISNUMBER(F7)),E7-F7,"") | H7: 10.9 | I7: -25.3 | J7: CR 25/223 (rebased non-oil GDP) | K7: =IF(AND(ISNUMBER(H7),ISNUMBER(D7)),H7-D7,"") | L7: 4.8 | M7: -32.4 | N7: -29.5 | O7: =IF(AND(ISNUMBER(M7),ISNUMBER(N7)),M7-N7,"") | P7: CR 23/323 | Q7: =IF(AND(ISNUMBER(L7),ISNUMBER(D7)),L7-D7,"")
A8: 2023 | B8: CR 22/274 (2022 Art. IV) | C8: Aug 2022 | D8: 3.8 | E8: -26.1 | F8: -27.9 | G8: =IF(AND(ISNUMBER(E8),ISNUMBER(F8)),E8-F8,"") | H8: 5.8 | I8: -25.4 | J8: CR 25/223 | K8: =IF(AND(ISNUMBER(H8),ISNUMBER(D8)),H8-D8,"") | L8: 3.8 | M8: -33 | N8: -32.2 | O8: =IF(AND(ISNUMBER(M8),ISNUMBER(N8)),M8-N8,"") | P8: CR 24/280 | Q8: =IF(AND(ISNUMBER(L8),ISNUMBER(D8)),L8-D8,"")
A9: 2024 | B9: CR 23/323 (2023 Art. IV) | C9: Sep 2023 | D9: 4.4 | E9: -25.8 | F9: -27.4 | G9: =IF(AND(ISNUMBER(E9),ISNUMBER(F9)),E9-F9,"") | H9: 4.5 | I9: -24.7 | J9: CR 25/223 | K9: =IF(AND(ISNUMBER(H9),ISNUMBER(D9)),H9-D9,"") | L9: 4.5 | M9: -24.7 | N9: -25.4 | O9: =IF(AND(ISNUMBER(M9),ISNUMBER(N9)),M9-N9,"") | P9: CR 25/223 (rebased non-oil GDP) | Q9: =IF(AND(ISNUMBER(L9),ISNUMBER(D9)),L9-D9,"")
A10: 2025 | B10: CR 24/280 (2024 Art. IV) | C10: Sep 2024 | D10: 4.4 | E10: -30.4 | F10: -32.4 | G10: =IF(AND(ISNUMBER(E10),ISNUMBER(F10)),E10-F10,"") | J10: n.a. - 2026 Art. IV report due ~Aug 2026; PR 26/181: real GDP +4.5% in 2025 | K10: =IF(AND(ISNUMBER(H10),ISNUMBER(D10)),H10-D10,"") | O10: =IF(AND(ISNUMBER(M10),ISNUMBER(N10)),M10-N10,"") | P10: n.a. | Q10: =IF(AND(ISNUMBER(L10),ISNUMBER(D10)),L10-D10,"")
A11: 2026 | B11: CR 25/223 (2025 Art. IV) | C11: Aug 2025 | D11: 3.5 | E11: -20.3 | F11: -21.1 | G11: =IF(AND(ISNUMBER(E11),ISNUMBER(F11)),E11-F11,"") | J11: n.a. (year in progress) | K11: =IF(AND(ISNUMBER(H11),ISNUMBER(D11)),H11-D11,"") | O11: =IF(AND(ISNUMBER(M11),ISNUMBER(N11)),M11-N11,"") | P11: n.a. | Q11: =IF(AND(ISNUMBER(L11),ISNUMBER(D11)),L11-D11,"")
A13: Notes: 2021 - no IMF vintage (2020 Article IV skipped, COVID). 2025/2026 - IMF actuals not yet published. 2022 latest actual & 2024 first outturn are on GASTAT's rebased national accounts (CR 25/223 basis), not the basis of older vintages. 2019 'Actual NOPB t-1 same report' is n.a. because CR 21/149's table starts in 2019.

Sheet Regression
A1: Blanchard-Leigh regression: FE(t) = alpha + beta * planned ΔNOPB(t)
A2: Live formulas (SLOPE/INTERCEPT/LINEST over the complete-case block below). Delete a row from the block to test sensitivity.
A4: Complete observations
A5: Budget year | B5: Planned ΔNOPB (pp) | C5: FE latest (pp) | D5: FE first outturn (pp)
A6: 2017 | B6: =Data!G2 | C6: =Data!K2 | D6: =Data!Q2
A7: 2018 | B7: =Data!G3 | C7: =Data!K3 | D7: =Data!Q3
A8: 2019 | B8: =Data!G4 | C8: =Data!K4 | D8: =Data!Q4
A9: 2020 | B9: =Data!G5 | C9: =Data!K5 | D9: =Data!Q5
A10: 2022 | B10: =Data!G7 | C10: =Data!K7 | D10: =Data!Q7
A11: 2023 | B11: =Data!G8 | C11: =Data!K8 | D11: =Data!Q8
A12: 2024 | B12: =Data!G9 | C12: =Data!K9 | D12: =Data!Q9
A14: Statistic | B14: vs latest actuals | C14: vs first outturn
A15: beta (slope) | B15: =SLOPE(C6:C12,B6:B12) | C15: =SLOPE(D6:D12,B6:B12)
A16: s.e. of beta | B16: =INDEX(LINEST(C6:C12,B6:B12,TRUE,TRUE),2,1) | C16: =INDEX(LINEST(D6:D12,B6:B12,TRUE,TRUE),2,1)
A17: t-stat of beta | B17: =SLOPE(C6:C12,B6:B12)/INDEX(LINEST(C6:C12,B6:B12,TRUE,TRUE),2,1) | C17: =SLOPE(D6:D12,B6:B12)/INDEX(LINEST(D6:D12,B6:B12,TRUE,TRUE),2,1)
A18: alpha (intercept) | B18: =INTERCEPT(C6:C12,B6:B12) | C18: =INTERCEPT(D6:D12,B6:B12)
A19: R-squared | B19: =RSQ(C6:C12,B6:B12) | C19: =RSQ(D6:D12,B6:B12)
A20: n | B20: =COUNT(C6:C12) | C20: =COUNT(D6:D12)
A22: Pre-computed (statsmodels OLS): latest actuals, full n=7: beta=-0.21 (se 1.11, p=0.86); excl. 2020: beta=-0.31 (p=0.75); excl. 2020&2022: beta=+0.06 (p=0.89).
A23: First-outturn actuals, full n=7: beta=+0.30 (se 0.65, p=0.67); excl. 2020: +0.22 (p=0.51); excl. 2020&2022: +0.30 (p=0.40). No specification is significant; sample too short for inference.

Sheet Chart
A1: Non-oil growth forecast error vs planned change in non-oil primary balance (IMF pre-budget vintages)
A29: Interactive Excel chart: series 1 (blue circles) uses latest IMF actuals with a linear trendline; series 2 (violet diamonds) uses first-outturn actuals.
A30: Static labeled version with year annotations: see chart.png in the repository.

Sheet Sources
A1: Role | B1: Document | C1: Published | D1: Values used | E1: URL / archive
A2: Vintage t=2017 | B2: IMF CR 16/326, 2016 Article IV staff report | C2: Oct 2016 | D2: Table 1 p.41: non-oil growth 2016-17; NOPB 2016-17 | E2: https://www.imf.org/en/Publications/CR/Issues/2016/12/31/Saudi-Arabia-2016-Article-IV-Consultation-Press-Release-Staff-Report-and-Informational-Annex-44328 | data/imf_reports/imf_sau_artiv_2016_cr16326.pdf
A3: Vintage t=2018 | B3: IMF CR 17/316, 2017 Article IV staff report | C3: Oct 2017 | D3: Table 1 p.41: non-oil growth 2017-18; NOPB 2017-18 | E3: https://www.imf.org/en/Publications/CR/Issues/2017/10/05/Saudi-Arabia-2017-Article-IV-Consultation-Press-Release-and-Staff-Report-45312 | data/imf_reports/imf_sau_artiv_2017_cr17316.pdf
A4: Vintage t=2019 | B4: IMF CR 18/263, 2018 Article IV staff report | C4: Aug 2018 | D4: Table 1 p.41: non-oil growth 2018-19; NOPB 2018-19 | E4: https://www.imf.org/en/Publications/CR/Issues/2018/08/24/Saudi-Arabia-2018-Article-IV-Consultation-Press-Release-and-Staff-Report-46195 | data/imf_reports/imf_sau_artiv_2018_cr18263.pdf
A5: Vintage t=2020 | B5: IMF CR 19/290, 2019 Article IV staff report | C5: Sep 2019 | D5: Table 1 p.44: non-oil growth 2019-20; NOPB 2019-20; also latest actuals for 2017-18 | E5: https://www.imf.org/en/Publications/CR/Issues/2019/09/09/Saudi-Arabia-2019-Article-IV-Consultation-Press-Release-and-Staff-Report-48659 | data/imf_reports/imf_sau_artiv_2019_cr19290.pdf
A6: (t=2021) | B6: No 2020 Article IV consultation (COVID-19); no IMF non-oil vintage near the Dec-2020 budget | C6: - | D6: - | E6: -
A7: Vintage t=2022 | B7: IMF CR 21/149, 2021 Article IV staff report | C7: Jul 2021 | D7: Table 1 p.40: non-oil growth 2021-22; NOPB 2021-22; first outturn for 2019-20 | E7: https://www.imf.org/en/Publications/CR/Issues/2021/07/07/Saudi-Arabia-2021-Article-IV-Consultation-Press-Release-and-Staff-Report-461736 | data/imf_reports/imf_sau_artiv_2021_cr21149.pdf
A8: Vintage t=2023 | B8: IMF CR 22/274, 2022 Article IV staff report | C8: Aug 2022 | D8: Table 1 p.45: non-oil growth 2022-23; NOPB 2022-23; first outturn for 2021 | E8: https://www.imf.org/en/publications/cr/issues/2022/08/11/saudi-arabia-2022-article-iv-consultation-press-release-and-staff-report-522189 | data/imf_reports/imf_sau_artiv_2022_cr22274.pdf
A9: Vintage t=2024 | B9: IMF CR 23/323, 2023 Article IV staff report | C9: Sep 2023 | D9: Table 1 p.49: non-oil growth 2023-24; NOPB 2023-24; latest actuals for 2019; first outturn for 2022 | E9: https://www.imf.org/en/publications/cr/issues/2023/09/05/saudi-arabia-2023-article-iv-consultation-press-release-staff-report-and-informational-annex-538823 | data/imf_reports/imf_sau_artiv_2023_cr23323.pdf
A10: Vintage t=2025 | B10: IMF CR 24/280, 2024 Article IV staff report | C10: Sep 2024 | D10: Table 1 p.52: non-oil growth 2024-25; NOPB 2024-25; latest actuals for 2020-21; first outturn for 2023 | E10: https://www.imf.org/en/Publications/CR/Issues/2024/09/03/Saudi-Arabia-2024-Article-IV-Consultation-Press-Release-Staff-Report-and-Informational-Annex-554530 | data/imf_reports/imf_sau_artiv_2024_cr24280.pdf
A11: Vintage t=2026 | B11: IMF CR 25/223, 2025 Article IV staff report | C11: Aug 2025 | D11: Table 1 p.43: non-oil growth 2025-26; NOPB 2025-26; latest actuals for 2022-24 (rebased basis) | E11: https://www.imf.org/en/publications/cr/issues/2025/08/02/saudi-arabia-2025-article-iv-consultation-press-release-and-staff-report-569252 | data/imf_reports/imf_sau_artiv_2025_cr25223.pdf
A12: 2025 memo | B12: IMF Press Release 26/181, staff completes 2026 Article IV mission | C12: 3 Jun 2026 | D12: Real GDP +4.5% in 2025 (total; non-oil actual not yet published) | E12: https://www.imf.org/en/news/articles/2026/06/03/pr26181-saudi-arabia-imf-staff-completes-2026-article-iv-mission
A13: Method | B13: Blanchard, O. and D. Leigh (2013), 'Growth Forecast Errors and Fiscal Multipliers', AER 103(3) / IMF WP/13/1 | C13: 2013 | D13: Regression design | E13: https://www.imf.org/external/pubs/ft/wp/2013/wp1301.pdf
